{
  "text-color": "#414c63",
  "links-color": "#4b6fd7",
  "light-color": "#414c63",
  "white-color": "#fff",
  "stroke-color": "#eaeaea",
  "tag-color": "#7aa0c5",
  "slider-active-color": "#f29400",
  "slider-button": "#2d3c4e",
  "footer-color": "#1f232d",
  "linear-startcolor": "#ad00ed",
  "linear-endcolor": "#5500f2",
  "linear-startcolor-hover": "#bb02ff",
  "linear-endcolor-hover": "#610cff",
  "active-menu-color": "#5500f2",
  "hover-menu-color":"3a414e",

  "bp-desktop-hd": "1800px",
  "bp-desktop": "1200px",  
  "bp-tablets": "768px",
  "bp-phones": "480px",
  "bp-phones-small": "320px",

  "bp-desktop1350": "1350px",
  "bp-desktop1110": "1110px",
  "bp-desktop960": "960px",

  "light": 300,
  "regular": 400,
  "semi-bold": 600,
  "bold": 700,
  "extra-bold": 800
}

